{
  "id": "15f6c038-9249-494a-9d33-9030831736fb",
  "revision": 0,
  "last_node_id": 33,
  "last_link_id": 66,
  "nodes": [
    {
      "id": 27,
      "type": "UniRigLoadMesh",
      "pos": [
        -353.1439374944664,
        -449.70633036831504
      ],
      "size": [
        270,
        82
      ],
      "flags": {},
      "order": 0,
      "mode": 0,
      "inputs": [],
      "outputs": [
        {
          "name": "mesh",
          "type": "TRIMESH",
          "links": [
            62
          ]
        }
      ],
      "properties": {
        "aux_id": "PozzettiAndrea/ComfyUI-UniRig",
        "ver": "66be51b5fe9fb85dca17918f23822cf0cad7b927",
        "Node name for S&R": "UniRigLoadMesh",
        "cnr_id": "comfyui-unirig"
      },
      "widgets_values": [
        "input",
        "3d/realistic_male_character.glb"
      ]
    },
    {
      "id": 20,
      "type": "UniRigLoadSkeletonModel",
      "pos": [
        -358.14082619153857,
        -312.5579959841866
      ],
      "size": [
        281.230078125,
        82
      ],
      "flags": {},
      "order": 1,
      "mode": 0,
      "inputs": [],
      "outputs": [
        {
          "name": "skeleton_model",
          "type": "UNIRIG_SKELETON_MODEL",
          "links": [
            63
          ]
        }
      ],
      "properties": {
        "aux_id": "PozzettiAndrea/ComfyUI-UniRig",
        "ver": "d135802ee8a1591a8614963ce4e61cd823de61b2",
        "Node name for S&R": "UniRigLoadSkeletonModel",
        "cnr_id": "comfyui-unirig"
      },
      "widgets_values": [
        "VAST-AI/UniRig",
        true
      ]
    },
    {
      "id": 22,
      "type": "UniRigLoadSkinningModel",
      "pos": [
        -358.5598359571634,
        -177.24232528106091
      ],
      "size": [
        280.45078125,
        82
      ],
      "flags": {},
      "order": 2,
      "mode": 0,
      "inputs": [],
      "outputs": [
        {
          "name": "skinning_model",
          "type": "UNIRIG_SKINNING_MODEL",
          "links": [
            64
          ]
        }
      ],
      "properties": {
        "aux_id": "PozzettiAndrea/ComfyUI-UniRig",
        "ver": "d135802ee8a1591a8614963ce4e61cd823de61b2",
        "Node name for S&R": "UniRigLoadSkinningModel",
        "cnr_id": "comfyui-unirig"
      },
      "widgets_values": [
        "VAST-AI/UniRig",
        true
      ]
    },
    {
      "id": 33,
      "type": "UniRigAutoRig",
      "pos": [
        3.5286291532608423,
        -458.573692277461
      ],
      "size": [
        284.70703125,
        290
      ],
      "flags": {},
      "order": 3,
      "mode": 0,
      "inputs": [
        {
          "name": "trimesh",
          "type": "TRIMESH",
          "link": 62
        },
        {
          "name": "skeleton_model",
          "type": "UNIRIG_SKELETON_MODEL",
          "link": 63
        },
        {
          "name": "skinning_model",
          "type": "UNIRIG_SKINNING_MODEL",
          "link": 64
        }
      ],
      "outputs": [
        {
          "name": "fbx_output_path",
          "type": "STRING",
          "links": [
            66
          ]
        }
      ],
      "properties": {
        "aux_id": "PozzettiAndrea/ComfyUI-UniRig",
        "ver": "7720a053ac54d893bef0d04051f02bc07e27dfc6",
        "Node name for S&R": "UniRigAutoRig"
      },
      "widgets_values": [
        "mixamo",
        "rigged_human",
        3361360550,
        "randomize",
        50000,
        196,
        32768,
        8192,
        0.5
      ]
    },
    {
      "id": 10,
      "type": "UniRigPreviewRiggedMesh",
      "pos": [
        385.2032818700097,
        -461.0714744862015
      ],
      "size": [
        842.8834804687501,
        822
      ],
      "flags": {},
      "order": 4,
      "mode": 0,
      "inputs": [
        {
          "name": "fbx_output_path",
          "type": "STRING",
          "widget": {
            "name": "fbx_output_path"
          },
          "link": 66
        },
        {
          "name": "rigged_mesh",
          "type": "RIGGED_MESH",
          "link": null
        }
      ],
      "outputs": [],
      "properties": {
        "aux_id": "PozzettiAndrea/ComfyUI-UniRig",
        "ver": "31be2f3349eb643d1255cc3280596968a762e0f6",
        "Node name for S&R": "UniRigPreviewRiggedMesh",
        "cnr_id": "comfyui-unirig"
      },
      "widgets_values": [
        "",
        ""
      ]
    }
  ],
  "links": [
    [
      62,
      27,
      0,
      33,
      0,
      "TRIMESH"
    ],
    [
      63,
      20,
      0,
      33,
      1,
      "UNIRIG_SKELETON_MODEL"
    ],
    [
      64,
      22,
      0,
      33,
      2,
      "UNIRIG_SKINNING_MODEL"
    ],
    [
      66,
      33,
      0,
      10,
      0,
      "STRING"
    ]
  ],
  "groups": [],
  "config": {},
  "extra": {
    "ds": {
      "scale": 0.8264462809917354,
      "offset": [
        844.9472886540738,
        800.6439101881016
      ]
    },
    "frontendVersion": "1.36.13",
    "workflowRendererVersion": "LG"
  },
  "version": 0.4
}